{"data":{"allMarkdownRemark":{"edges":[{"node":{"frontmatter":{"title":"A page about the sport I love!","date":"2019-04-24"},"html":"<p>Talking baseball.</p>","excerpt":"Talking baseball."}},{"node":{"frontmatter":{"title":"Building Sites with Gatsby","date":"2019-04-23"},"html":"<p>I'm building sites with Gatsby</p>\n<h2>Topics covered are</h2>\n<ol>\n<li>Gatsby</li>\n<li>GraphQL</li>\n<li>Markdown</li>\n<li>React</li>\n</ol>","excerpt":"I'm building sites with Gatsby Topics covered are Gatsby GraphQL Markdown React"}}]}}}